xmi/.DS_Store
xmi/__init__.py
xmi/v1/__init__.py
xmi/v1/constants.py
xmi/v1/entities/__init__.py
xmi/v1/entities/xmi_material.py
xmi/v1/entities/xmi_segment.py
xmi/v1/entities/xmi_structural_cross_section.py
xmi/v1/entities/xmi_structural_curve_member.py
xmi/v1/entities/xmi_structural_material.py
xmi/v1/entities/xmi_structural_point_connection.py
xmi/v1/entities/xmi_structural_storey.py
xmi/v1/entities/xmi_structural_surface_member.py
xmi/v1/entities/xmi_structural_unit.py
xmi/v1/enums/__init__.py
xmi/v1/enums/xmi_enums.py
xmi/v1/enums/xmi_material_enums.py
xmi/v1/enums/xmi_shape_enums.py
xmi/v1/enums/xmi_structural_curve_member_enums.py
xmi/v1/enums/xmi_structural_material_enums.py
xmi/v1/enums/xmi_structural_surface_member_enums.py
xmi/v1/geometries/__init__.py
xmi/v1/geometries/xmi_arc_3d.py
xmi/v1/geometries/xmi_base_geometry.py
xmi/v1/geometries/xmi_line_3d.py
xmi/v1/geometries/xmi_point_3d.py
xmi/v1/relationships/__init__.py
xmi/v1/relationships/xmi_has_geometry.py
xmi/v1/relationships/xmi_has_line_3d.py
xmi/v1/relationships/xmi_has_point_3d.py
xmi/v1/relationships/xmi_has_segment.py
xmi/v1/relationships/xmi_has_structural_cross_section.py
xmi/v1/relationships/xmi_has_structural_material.py
xmi/v1/relationships/xmi_has_structural_node.py
xmi/v1/shapes/__init__.py
xmi/v1/shapes/xmi_shape.py
xmi/v1/xmi_base.py
xmi/v1/xmi_errors.py
xmi/v1/xmi_manager.py
xmi/v1/xmi_model.py
xmi/v1/xmi_utilities.py
xmi/v2/.DS_Store
xmi/v2/__init__.py
xmi/v2/models/__init__.py
xmi/v2/models/bases/XmiBaseEntity.md
xmi/v2/models/bases/XmiBaseEnum.md
xmi/v2/models/bases/XmiBaseGeometry.md
xmi/v2/models/bases/XmiBaseRelationship.md
xmi/v2/models/bases/__init__.py
xmi/v2/models/bases/xmi_base_entity.py
xmi/v2/models/bases/xmi_base_enum.py
xmi/v2/models/bases/xmi_base_geometry.py
xmi/v2/models/bases/xmi_base_physical_entity.py
xmi/v2/models/bases/xmi_base_relationship.py
xmi/v2/models/bases/xmi_base_structural_analytical_entity.py
xmi/v2/models/entities/XmiCrossSection.md
xmi-0.5.0.dist-info/METADATA
xmi-0.5.0.dist-info/WHEEL
xmi-0.5.0.dist-info/licenses/LICENSE.txt
xmi-0.5.0.dist-info/RECORD
