Metadata-Version: 2.4
Name: xmi
Version: 0.5.0
Summary: Used to interpret XMI Schema
License: MIT
License-File: LICENSE.txt
Keywords: xmi,schema,structural,engineering
Author: darellchua
Author-email: darellchua2@gmail.com
Requires-Python: >=3.12
Classifier: Development Status :: 4 - Beta
Classifier: Intended Audience :: Developers
Classifier: License :: OSI Approved :: MIT License
Classifier: Programming Language :: Python :: 3
Classifier: Programming Language :: Python :: 3.12
Classifier: Programming Language :: Python :: 3.13
Requires-Dist: pydantic (>=2.12.5,<3.0.0)
Project-URL: Bug Tracker, https://github.com/darellchua2/xmi-schema/issues
Project-URL: Documentation, https://github.com/darellchua2/xmi-schema
Project-URL: Homepage, https://github.com/darellchua2/xmi-schema
Project-URL: Repository, https://github.com/darellchua2/xmi-schema
